mkdocs_callouts_codeblock/__init__.py
mkdocs_callouts_codeblock/plugin.py
mkdocs_callouts_codeblock/utils.py
mkdocs_callouts_codeblock-1.16.5.dist-info/LICENSE
mkdocs_callouts_codeblock-1.16.5.dist-info/METADATA
mkdocs_callouts_codeblock-1.16.5.dist-info/WHEEL
mkdocs_callouts_codeblock-1.16.5.dist-info/entry_points.txt
mkdocs_callouts_codeblock-1.16.5.dist-info/top_level.txt
mkdocs_callouts_codeblock-1.16.5.dist-info/RECORD
